pytest_evals/__init__.py
pytest_evals/ipython_extension.py
pytest_evals/json_encoder.py
pytest_evals/models.py
pytest_evals/plugin.py
pytest_evals-0.3.4.dist-info/METADATA
pytest_evals-0.3.4.dist-info/WHEEL
pytest_evals-0.3.4.dist-info/entry_points.txt
pytest_evals-0.3.4.dist-info/licenses/LICENSE
pytest_evals-0.3.4.dist-info/RECORD
