Metadata-Version: 2.4
Name: pytest-evals
Version: 0.3.4
Summary: A pytest plugin for running and analyzing LLM evaluation tests
Project-URL: Homepage, https://github.com/AlmogBaku/pytest-evals
Project-URL: Repository, https://github.com/AlmogBaku/pytest-evals
Project-URL: Issues, https://github.com/AlmogBaku/pytest-evals/issues
Author-email: Almog Baku <almog.baku@gmail.com>
License-Expression: MIT
License-File: LICENSE
Keywords: anthropic,eval,evaluations,gpt,llm,openai,pytest,pytest-evals
Requires-Python: >=3.9
Requires-Dist: cloudpickle>=2.0.0
Requires-Dist: pytest-harvest>=1.0.0
Requires-Dist: pytest>=7.0.0
